[
  {
    "id": 1,
    "platform": "Instagram",
    "icon": "Instagram",
    "href": "https://instagram.com/beionmarketing",
    "color": "hover:text-pink-400"
  },
  {
    "id": 2,
    "platform": "Facebook",
    "icon": "Facebook",
    "href": "https://facebook.com/beionmarketing",
    "color": "hover:text-blue-400"
  },
  {
    "id": 3,
    "platform": "WhatsApp",
    "icon": "MessageCircle",
    "href": "https://wa.me/923001234567",
    "color": "hover:text-green-400"
  },
  {
    "id": 4,
    "platform": "TikTok",
    "icon": "Music2",
    "href": "https://tiktok.com/@beionmarketing",
    "color": "hover:text-white"
  },
  {
    "id": 5,
    "platform": "LinkedIn",
    "icon": "Linkedin",
    "href": "https://linkedin.com/company/beionmarketing",
    "color": "hover:text-blue-300"
  }
]
